example_package_edubarse_attempt_1/__init__.py
example_package_edubarse_attempt_1/ejemplo.py
example_package_edubarse_attempt_1/question2.py
example_package_edubarse_attempt_1-0.0.1.dist-info/LICENSE
example_package_edubarse_attempt_1-0.0.1.dist-info/METADATA
example_package_edubarse_attempt_1-0.0.1.dist-info/WHEEL
example_package_edubarse_attempt_1-0.0.1.dist-info/top_level.txt
example_package_edubarse_attempt_1-0.0.1.dist-info/RECORD
