Metadata-Version: 2.1
Name: example-package-edubarse-attempt-1
Version: 0.0.1
Summary: toy attempt for SITA challenge
Author-email: Eduardo Barseghian <edubarse@gmail.com>
Project-URL: Homepage, https://github.com/pypa/sampleproject
Project-URL: Bug Tracker, https://github.com/pypa/sampleproject/issues
Classifier: Programming Language :: Python :: 3
Classifier: License :: OSI Approved :: MIT License
Classifier: Operating System :: OS Independent
Requires-Python: >=3.8
License-File: LICENSE
